fuzzycollections/__init__.py
fuzzycollections/fuzzycollections.py
fuzzycollections/py.typed
fuzzycollections-0.0.4.dist-info/WHEEL
fuzzycollections-0.0.4.dist-info/METADATA
fuzzycollections-0.0.4.dist-info/RECORD
